pshape/__init__.py
pshape/exceptions.py
pshape/identify_backend.py
pshape/metrics.py
pshape/pshape.py
pshape-0.2.1.dist-info/LICENCE.txt
pshape-0.2.1.dist-info/METADATA
pshape-0.2.1.dist-info/WHEEL
pshape-0.2.1.dist-info/top_level.txt
pshape-0.2.1.dist-info/RECORD
