Metadata-Version: 2.1
Name: pshape
Version: 0.2.1
Summary: Prints NumPy-like arrays' shapes, mins, means, and maxes, as well as the names of the input variable outside the functions' scope
Home-page: https://github.com/sam1902/pshape
Author: Samuel Prevost
Author-email: samuel.prevost@pm.me
License: BSD
Platform: UNKNOWN
Classifier: License :: OSI Approved :: BSD License
Classifier: Programming Language :: Python :: 3
Classifier: Programming Language :: Python :: 3.8
License-File: LICENCE.txt
Requires-Dist: numpy
